{
  "source": {
    "source_id": "source_cf82addf2c1d74e1",
    "tenant_id": "chejin",
    "layer": "tenant",
    "source_type": "wechat_raw_message",
    "category": "private",
    "product_id": "",
    "source_path": "D:\\AI\\omniauto\\runtime\\apps\\wechat_ai_customer_service\\tenants\\chejin\\raw_messages\\learning_batches\\raw_batch_9fbdafc315dffa9e4b3e.txt",
    "content_hash": "c2642b4eec026216fc51dbc7eb55f35f",
    "status": "quarantined",
    "created_at": "2026-05-06T22:09:41",
    "updated_at": "2026-05-06T22:09:41",
    "quarantine_reason": "raw_wechat_source_not_directly_retrievable"
  },
  "chunks": [
    {
      "chunk_id": "chunk_980a21fb8974786b",
      "source_id": "source_cf82addf2c1d74e1",
      "tenant_id": "chejin",
      "layer": "tenant",
      "source_type": "wechat_raw_message",
      "category": "private",
      "product_id": "",
      "source_path": "D:\\AI\\omniauto\\runtime\\apps\\wechat_ai_customer_service\\tenants\\chejin\\raw_messages\\learning_batches\\raw_batch_9fbdafc315dffa9e4b3e.txt",
      "chunk_index": 0,
      "text": "[2026-05-06 22:09:00] system: 22:09",
      "char_count": 35,
      "status": "quarantined",
      "created_at": "2026-05-06T22:09:41",
      "quarantine_reason": "raw_wechat_source_not_directly_retrievable",
      "quarantined_at": "2026-05-19T01:47:04"
    }
  ]
}
